ModNCounter.v
module ModNCounter (
	input clk,    // Clock
	input clr,  // Asynchronous clear
	output [1:0]Q
);

reg [1:0]Q;

always @(posedge clk or negedge clr) 
begin 
	if(~clr) 
	begin
		Q <= 2'b00;
	end 

	else if(Q == 2'b10)
	begin 
		Q <= 2'b00;
	end

	else 
	begin
		Q <= Q + 1;
	end
end

endmodule

ModNCounter_tb.v
`timescale 1s/100ms
`include "ModNCounter.v"

module ModNCounter_tb ();

	reg clk;
	reg clr;
	wire [1:0]Q;

	ModNCounter myCounter(clk, clr, Q);

	initial
	begin 
		$monitor("Count = %b", Q);
		$dumpfile("modNCounter.vcd");
		$dumpvars(0, ModNCounter_tb);

		clr <= 0;
		clk <= 1; #1;
		clr <= 1;
		clk <= 0; #1; //Count 0

		clk <= 1; #1;
		clk <= 0; #1; //Count 1

		clk <= 1; #1;
		clk <= 0; #1; //Count 2

		clk <= 1; #1;
		clk <= 0; #1; //Count 0

		clk <= 1; #1;
		clk <= 0; #1; //Count 1

		clk <= 1; #1;
		clk <= 0; #1; //Count 2

		clk <= 1; #1;
		clk <= 0; #1; //Count 0

		clk <= 1; #1;
		clk <= 0; #1; //Count 1

		clk <= 1; #1;
		clk <= 0; #1; //Count 2

		clk <= 1; #1;
		clk <= 0; #1; //Count 0

		clk <= 1; #1;
		clk <= 0; #1; //Count 1


		clr <= 0;
		clk <= 1; #1;
		clr <= 1;
		clk <= 0; #1; //Count 0


		clk <= 1; #1;
		clk <= 0; #1; //Count 1

		clk <= 1; #1;
		clk <= 0; #1; //Count 2

		$finish;
	end

endmodule

modNCounter.vcd
$date
	Mon Nov 12 23:22:25 2018
$end
$version
	Icarus Verilog
$end
$timescale
	100ms
$end
$scope module ModNCounter_tb $end
$var wire 2 ! Q [1:0] $end
$var reg 1 " clk $end
$var reg 1 # clr $end
$scope module myCounter $end
$var wire 1 " clk $end
$var wire 1 # clr $end
$var reg 2 $ Q [1:0] $end
$upscope $end
$upscope $end
$enddefinitions $end
#0
$dumpvars
b0 $
0#
1"
b0 !
$end
#10
0"
1#
#20
b1 !
b1 $
1"
#30
0"
#40
b10 !
b10 $
1"
#50
0"
#60
b0 !
b0 $
1"
#70
0"
#80
b1 !
b1 $
1"
#90
0"
#100
b10 !
b10 $
1"
#110
0"
#120
b0 !
b0 $
1"
#130
0"
#140
b1 !
b1 $
1"
#150
0"
#160
b10 !
b10 $
1"
#170
0"
#180
b0 !
b0 $
1"
#190
0"
#200
b1 !
b1 $
1"
#210
0"
#220
b0 !
b0 $
1"
0#
#230
0"
1#
#240
b1 !
b1 $
1"
#250
0"
#260
b10 !
b10 $
1"
